manish/__init__.py
manish/button.py
manish/contact.py
manish/helpers.py
manish/location.py
manish/template.py
ma_nish-1.3.2.dist-info/LICENSE
ma_nish-1.3.2.dist-info/METADATA
ma_nish-1.3.2.dist-info/WHEEL
ma_nish-1.3.2.dist-info/top_level.txt
ma_nish-1.3.2.dist-info/RECORD
