Metadata-Version: 2.1
Name: ma-nish
Version: 1.3.2
Summary: manish is an unofficial python wrapper for Whatsapp cloud api
Home-page: https://github.com/t0mer/ma-nish
Download-URL: https://pypi.org/project/ma-nish/
Author: Tomer Klein
Author-email: tomer.klein@gmail.com
License: MIT
Project-URL: Documentation, https://github.com/t0mer/ma-nish
Project-URL: Source, https://github.com/t0mer/ma-nish
Keywords: meta,ma-nish,facebook,whatsapp
License-File: LICENSE
Requires-Dist: python-dotenv
Requires-Dist: requests
Requires-Dist: requests-toolbelt
Requires-Dist: validators
Requires-Dist: geopy
Requires-Dist: Pillow
Requires-Dist: loguru
Requires-Dist: uvicorn
Requires-Dist: fastapi
Requires-Dist: jinja2
Requires-Dist: dataclasses-json
